goodtogo/cli.py
goodtogo/files.py
goodtogo/langs.py
goodtogo/pdf.py
goodtogo/scraper.py
goodtogo-0.1.0.dist-info/METADATA
goodtogo-0.1.0.dist-info/WHEEL
goodtogo-0.1.0.dist-info/entry_points.txt
goodtogo-0.1.0.dist-info/RECORD
