Metadata-Version: 2.3
Name: goodtogo
Version: 0.1.0
Summary: Check if your AP CSP personal project is ready for submission, scrape comments and help document
Author: Sam Perillo
Author-email: sam@perillo.dev
Requires-Python: >=3.13
Classifier: Programming Language :: Python :: 3
Classifier: Programming Language :: Python :: 3.13
Requires-Dist: click (>=8.1.8,<9.0.0)
Requires-Dist: colorama (>=0.4.6,<0.5.0)
Requires-Dist: inquirer (>=3.4.0,<4.0.0)
Requires-Dist: jsonmerge (>=1.9.2,<2.0.0)
Requires-Dist: markdown-pdf (>=1.3.3,<2.0.0)
Requires-Dist: termcolor (>=2.5.0,<3.0.0)
Requires-Dist: xhtml2pdf (>=0.2.17,<0.3.0)
